{
  "TemplateId": "observation_walkway",
  "Biome": "the_roots",
  "Size": "Medium",
  "Archetype": "Corridor",
  "NameTemplates": [
    "The {Adjective} Observation Walkway",
    "The {Adjective} Viewing Passage",
    "The {Adjective} Overlook Corridor"
  ],
  "Adjectives": [
    "Elevated",
    "Suspended",
    "Precarious",
    "High",
    "Exposed"
  ],
  "DescriptionTemplates": [
    "An {Adjective} observation walkway spans a dark chasm below. {Detail}. The grated floor allows glimpses of the depths.",
    "This {Adjective} viewing passage once offered a panorama of the facility. {Detail}. Now it overlooks only ruins.",
    "You traverse an {Adjective} corridor high above the lower levels. {Detail}. The walkway creaks under your weight."
  ],
  "Details": [
    "Safety railings have corroded away in places",
    "Looking down through the grating reveals machinery far below",
    "The bridge sways slightly with your movement",
    "Broken observation windows line one wall",
    "Support cables sing in the faint air currents"
  ],
  "MinConnectionPoints": 2,
  "MaxConnectionPoints": 3,
  "ValidConnections": [
    "Corridor",
    "Chamber",
    "Junction"
  ],
  "Difficulty": "Medium",
  "Tags": [
    "Connector",
    "Elevated",
    "Atmospheric"
  ]
}
